{"lastUsed":1721248086222,"path":"C:\/Users\/sherd\/Documents\/GitHub\/smartmachine","projectCount":1,"recentFiles":[{"path":"\/smartmachine\/Core\/Src","parentWorkspace":"C:\/Users\/sherd\/Documents\/GitHub\/smartmachine","name":"main.c","lastModified":1721248035832,"locationURI":"file:\/C:\/Users\/sherd\/Documents\/GitHub\/smartmachine\/smartmachine\/Core\/Src\/main.c"},{"path":"\/smartmachine","parentWorkspace":"C:\/Users\/sherd\/Documents\/GitHub\/smartmachine","name":"smartmachine.ioc","lastModified":1721248023180,"locationURI":"file:\/C:\/Users\/sherd\/Documents\/GitHub\/smartmachine\/smartmachine\/smartmachine.ioc"}]}